strapp/__init__.py
strapp/click/__init__.py
strapp/click/resolver.py
strapp/click/sentry.py
strapp/click/testing.py
strapp/datadog.py
strapp/dramatiq/__init__.py
strapp/dramatiq/base.py
strapp/dramatiq/datadog.py
strapp/dramatiq/sentry.py
strapp/dramatiq/testing.py
strapp/flask/__init__.py
strapp/flask/base.py
strapp/flask/database.py
strapp/flask/decorators.py
strapp/flask/error.py
strapp/flask/route.py
strapp/http/client.py
strapp/http/request.py
strapp/logging.py
strapp/py.typed
strapp/sentry.py
strapp/sqlalchemy/__init__.py
strapp/sqlalchemy/model_base.py
strapp/sqlalchemy/mypy.py
strapp/sqlalchemy/session.py
strapp/sqlalchemy/testing.py
strapp-0.4.1.dist-info/LICENSE
strapp-0.4.1.dist-info/WHEEL
strapp-0.4.1.dist-info/METADATA
strapp-0.4.1.dist-info/RECORD
