Metadata-Version: 2.1
Name: strapp
Version: 0.4.1
Summary: 
Requires-Python: >=3.8,<4.0
Classifier: Programming Language :: Python :: 3
Classifier: Programming Language :: Python :: 3.8
Classifier: Programming Language :: Python :: 3.9
Classifier: Programming Language :: Python :: 3.10
Provides-Extra: click
Provides-Extra: datadog
Provides-Extra: dramatiq
Provides-Extra: flask
Provides-Extra: http
Provides-Extra: sentry
Provides-Extra: sqlalchemy
Requires-Dist: backoff; extra == "http"
Requires-Dist: click; extra == "click"
Requires-Dist: datadog; extra == "datadog"
Requires-Dist: dramatiq[redis]; extra == "dramatiq"
Requires-Dist: flask; extra == "flask"
Requires-Dist: flask_reverse_proxy; extra == "flask"
Requires-Dist: redis (>=4.3.4,<5.0.0); extra == "dramatiq"
Requires-Dist: requests; extra == "sentry"
Requires-Dist: sentry-sdk; extra == "sentry"
Requires-Dist: setuplog (>=0.2.2); extra == "http"
Requires-Dist: sqlalchemy[mypy] (>=1.4); extra == "sqlalchemy"
Requires-Dist: typing_extensions (>=3.10); python_version <= "3.10"
